README.rst
setup.py
openvpn2alidns/__init__.py
openvpn2alidns.egg-info/PKG-INFO
openvpn2alidns.egg-info/SOURCES.txt
openvpn2alidns.egg-info/dependency_links.txt
openvpn2alidns.egg-info/entry_points.txt
openvpn2alidns.egg-info/requires.txt
openvpn2alidns.egg-info/top_level.txt