Metadata-Version: 1.1
Name: openvpn2alidns
Version: 0.1.1
Summary: Convert OpenVPN Clients Configuration to Aliyun DNA Record
Home-page: https://github.com/genee-projects/openvpn2alidns
Author: Jia Huang
Author-email: iamfat@gmail.com
License: MIT
Keywords: o,p,e,n,v,p,n, ,a,l,i,y,u,n
Platform: UNKNOWN
Classifier: Development Status :: 3 - Alpha
Classifier: Intended Audience :: Developers
Classifier: Topic :: Utilities
Classifier: License :: OSI Approved :: MIT License
